Metadata-Version: 1.0
Name: marble
Version: 1.0
Summary: Study residential segregation, explore its different dimensions.
Home-page: http://github.com/scities/marble
Author: Remi Louf
Author-email: remi.louf@sciti.es
License: BSD
Platform: UNKNOWN
